qugrad/__init__.py
qugrad/_hilbert_space.py
qugrad/pulses.py
qugrad/systems/__init__.py
qugrad/systems/_systems.py
qugrad/systems/_systems.pyi
qugrad-1.0.2.dist-info/METADATA
qugrad-1.0.2.dist-info/WHEEL
qugrad-1.0.2.dist-info/licenses/LICENSE
qugrad-1.0.2.dist-info/RECORD
