Metadata-Version: 2.4
Name: qugrad
Version: 1.0.2
Summary: A Python package for quantum optimal control.
Project-URL: Homepage, https://github.com/Christopher-K-Long/QuGrad
Project-URL: Documentation, https://QuGrad.readthedocs.io/
Project-URL: Issues, https://github.com/Christopher-K-Long/QuGrad/issues
Project-URL: Changelog, https://github.com/Christopher-K-Long/QuGrad/blob/main/ChangeLog.md
Author: Crispin H. W. Barnes, Normann Mertig
Author-email: "Christopher K. Long" <ckl45@cam.ac.uk>
Maintainer-email: "Christopher K. Long" <ckl45@cam.ac.uk>
License-Expression: Apache-2.0
License-File: LICENSE
Keywords: control,optimal,quantum
Classifier: Development Status :: 5 - Production/Stable
Classifier: Intended Audience :: Science/Research
Classifier: Natural Language :: English
Classifier: Operating System :: OS Independent
Classifier: Programming Language :: Python :: 3
Classifier: Programming Language :: Python :: 3.9
Classifier: Programming Language :: Python :: 3.10
Classifier: Programming Language :: Python :: 3.11
Classifier: Programming Language :: Python :: 3.12
Classifier: Programming Language :: Python :: 3.13
Classifier: Programming Language :: Python :: 3.14
Classifier: Topic :: Scientific/Engineering :: Physics
Classifier: Topic :: Scientific/Engineering :: Quantum Computing
Requires-Python: >=3.9
Requires-Dist: numpy<3,>=1.21
Requires-Dist: py-ste==1.*
Requires-Dist: tensorflow==2.*
